cli/__init__.py
cli/cli.py
cli/commands/__init__.py
cli/commands/__version__.py
cli/commands/cd.py
cli/commands/cmdbase.py
cli/commands/config.py
cli/commands/const.py
cli/commands/get.py
cli/commands/info.py
cli/commands/ls.py
cli/commands/rm.py
cli/commands/search.py
cli/commands/select.py
cli/commands/studio.py
cli/commons/__init__.py
cli/commons/argument_parser.py
cli/commons/exceptions.py
cli/commons/loghandler.py
cli/commons/stdio.py
cli/commons/storage_builder.py
cli/resources/cd.example
cli/resources/config.example
cli/resources/default_cli_cfg.json
cli/resources/get.example
cli/resources/info.example
cli/resources/ls.example
cli/resources/rm.example
cli/resources/select.example
cli/resources/studio.example
cli/utils/__init__.py
cli/utils/admin.py
cli/utils/minio_ops/__init__.py
cli/utils/minio_ops/ops.py
cli/utils/oss_ops/__init__.py
cli/utils/oss_ops/ops.py
cli/utils/plot.py
cli/utils/query.py
cli/utils/views/cifar-10/cifar-10.py
cli/utils/views/cifar-10-auto/cifar-10-auto.py
cli/utils/views/coco-demo/coco-demo.py
cli/utils/views/coco-demo/src/__init__.py
cli/utils/views/coco-demo/src/constants/colors.py
cli/utils/views/coco-demo/src/types.py
cli/utils/views/coco-demo/src/utils/display.py
cli/utils/views/coco-demo/src/utils/draw_bbox.py
cli/utils/views/general_app.py
cli/utils/views/view.py
cli/utils/views/view_from_info.py
dsdl/__init__.py
dsdl/__version__.py
dsdl/cli.py
dsdl/dataset/__init__.py
dsdl/dataset/base_dataset.py
dsdl/dataset/check_dataset.py
dsdl/dataset/demo_dataset.py
dsdl/dataset/utils/__init__.py
dsdl/dataset/utils/check.py
dsdl/dataset/utils/commons.py
dsdl/dataset/utils/visualizer.py
dsdl/dsdl_library/class/cifar10-class-dom.yaml
dsdl/dsdl_library/class/coco-class-domain.yaml
dsdl/dsdl_library/class/mnist-class-dom.yaml
dsdl/dsdl_library/class/voc-class-domain.yaml
dsdl/dsdl_library/task/classification-template.yaml
dsdl/dsdl_library/task/object-detection.yaml
dsdl/dsdl_py_library/CIFAR10_test_data.py
dsdl/dsdl_py_library/__init__.py
dsdlsdk-0.1.0.post203.dist-info/entry_points.txt
dsdlsdk-0.1.0.post203.dist-info/METADATA
dsdlsdk-0.1.0.post203.dist-info/LICENSE
dsdlsdk-0.1.0.post203.dist-info/WHEEL
dsdlsdk-0.1.0.post203.dist-info/RECORD
