Metadata-Version: 2.1
Name: dsdlsdk
Version: 0.1.0.post203
Summary: made for opendatalab dsdl-sdk dev branch(ignore other branches).
Home-page: https://github.com/opendatalab/dsdl-sdk/tree/dev
License: Apache-2.0
Keywords: odl-cli,opendatalab,pjlab
Author: dsdl-team
Author-email: dsdl-team@pjlab.org.cn
Requires-Python: >=3.8, !=2.7.*, !=3.0.*, !=3.1.*, !=3.2.*, !=3.3.*, !=3.4.*, !=3.5.*, !=3.6.*, !=3.7.*
Classifier: Development Status :: 2 - Pre-Alpha
Classifier: Intended Audience :: Developers
Classifier: License :: OSI Approved :: Apache Software License
Classifier: Natural Language :: English
Classifier: Programming Language :: Python :: 3
Classifier: Programming Language :: Python :: 3.8
Classifier: Programming Language :: Python :: 3.9
Classifier: Programming Language :: Python :: 3.10
Classifier: Programming Language :: Python :: 3.11
Classifier: Programming Language :: Python :: 3
Classifier: Programming Language :: Python :: 3.10
Classifier: Programming Language :: Python :: 3.8
Classifier: Programming Language :: Python :: 3.9
Requires-Dist: Pillow (>=9.1.0,<10.0.0)
Requires-Dist: boto3 (>=1.26.14,<2.0.0)
Requires-Dist: click (>=8.1.3,<9.0.0)
Requires-Dist: dsdl (>=0.1.10.3,<0.2.0.0)
Requires-Dist: duckdb (>=0.6.0,<0.7.0)
Requires-Dist: human-readable (>=1.3.0,<2.0.0)
Requires-Dist: jinja2 (>=3.0.0,<4.0.0)
Requires-Dist: jsonmodels (>=2.6.0,<3.0.0)
Requires-Dist: loguru (>=0.6.0,<0.7.0)
Requires-Dist: matplotlib (>=3.6.2,<4.0.0)
Requires-Dist: networkx (>=2.8.4,<3.0.0)
Requires-Dist: opencv-python (>=4.6.0.66,<5.0.0.0)
Requires-Dist: oss2 (>=2.15.0,<3.0.0)
Requires-Dist: pandas (>=1.5.1,<2.0.0)
Requires-Dist: pexpect (>=4.8.0,<5.0.0)
Requires-Dist: prettytable (>=3.3.0,<4.0.0)
Requires-Dist: psutil (>=5.9.4,<6.0.0)
Requires-Dist: pyarrow (>=10.0.0,<11.0.0)
Requires-Dist: python-dotenv (>=0.21.0,<0.22.0)
Requires-Dist: pyyaml (>=6.0,<7.0)
Requires-Dist: rich (>=12.6.0,<13.0.0)
Requires-Dist: setuptools-scm (>=7.0.5,<8.0.0)
Requires-Dist: smart-open[all] (>=6.2.0,<7.0.0)
Requires-Dist: stqdm (>=0.0.4,<0.0.5)
Requires-Dist: streamlit (>=1.15.1,<2.0.0)
Requires-Dist: tabulate (>=0.9.0,<0.10.0)
Requires-Dist: termgraph (>=0.5.3,<0.6.0)
Requires-Dist: toml (>=0.10.2,<0.11.0)
Requires-Dist: tqdm (>=4.64.1,<5.0.0)
